biotas/__init__.py
biotas/false_positive.py
biotas/fish_history.py
biotas/formatter.py
biotas/overlap_removal.py
biotas/radio_project.py
biotas/table_merge.py
biotas-0.0.10.dist-info/LICENSE.txt
biotas-0.0.10.dist-info/METADATA
biotas-0.0.10.dist-info/WHEEL
biotas-0.0.10.dist-info/top_level.txt
biotas-0.0.10.dist-info/RECORD
